py2hlog/__init__.py
py2hlog/addtree.py
py2hlog/html_files.py
py2hlog/logger.py
py2hlog-0.1.3.dist-info/LICENSE
py2hlog-0.1.3.dist-info/METADATA
py2hlog-0.1.3.dist-info/WHEEL
py2hlog-0.1.3.dist-info/top_level.txt
py2hlog-0.1.3.dist-info/RECORD
