Metadata-Version: 2.1
Name: py2hlog
Version: 0.1.3
Summary: Python logs to HTML formatter
Home-page: https://github.com/houshmand-2005/py2hlog
Author: houshmand
Author-email: houshmand2005@gmial.com
Project-URL: Bug Tracker, https://github.com/houshmand-2005/py2hlog
Classifier: Programming Language :: Python :: 3
Classifier: License :: OSI Approved :: MIT License
Classifier: Operating System :: OS Independent
Requires-Python: >=3.6
License-File: LICENSE
